sphinx_idf_theme/__init__.py
sphinx_idf_theme/breadcrumbs.html
sphinx_idf_theme/footer.html
sphinx_idf_theme/layout.html
sphinx_idf_theme/search.html
sphinx_idf_theme/searchbox.html
sphinx_idf_theme/theme.conf
sphinx_idf_theme/locale/sphinx.pot
sphinx_idf_theme/locale/de/LC_MESSAGES/sphinx.mo
sphinx_idf_theme/locale/de/LC_MESSAGES/sphinx.po
sphinx_idf_theme/locale/en/LC_MESSAGES/sphinx.mo
sphinx_idf_theme/locale/en/LC_MESSAGES/sphinx.po
sphinx_idf_theme/locale/es/LC_MESSAGES/sphinx.mo
sphinx_idf_theme/locale/es/LC_MESSAGES/sphinx.po
sphinx_idf_theme/locale/et/LC_MESSAGES/sphinx.mo
sphinx_idf_theme/locale/et/LC_MESSAGES/sphinx.po
sphinx_idf_theme/locale/fa_IR/LC_MESSAGES/sphinx.mo
sphinx_idf_theme/locale/fa_IR/LC_MESSAGES/sphinx.po
sphinx_idf_theme/locale/fr/LC_MESSAGES/sphinx.mo
sphinx_idf_theme/locale/fr/LC_MESSAGES/sphinx.po
sphinx_idf_theme/locale/it/LC_MESSAGES/sphinx.mo
sphinx_idf_theme/locale/it/LC_MESSAGES/sphinx.po
sphinx_idf_theme/locale/lt/LC_MESSAGES/sphinx.mo
sphinx_idf_theme/locale/lt/LC_MESSAGES/sphinx.po
sphinx_idf_theme/locale/nl/LC_MESSAGES/sphinx.mo
sphinx_idf_theme/locale/nl/LC_MESSAGES/sphinx.po
sphinx_idf_theme/locale/pl/LC_MESSAGES/sphinx.mo
sphinx_idf_theme/locale/pl/LC_MESSAGES/sphinx.po
sphinx_idf_theme/locale/pt/LC_MESSAGES/sphinx.mo
sphinx_idf_theme/locale/pt/LC_MESSAGES/sphinx.po
sphinx_idf_theme/locale/pt_BR/LC_MESSAGES/sphinx.mo
sphinx_idf_theme/locale/pt_BR/LC_MESSAGES/sphinx.po
sphinx_idf_theme/locale/ru/LC_MESSAGES/sphinx.mo
sphinx_idf_theme/locale/ru/LC_MESSAGES/sphinx.po
sphinx_idf_theme/locale/sv/LC_MESSAGES/sphinx.mo
sphinx_idf_theme/locale/sv/LC_MESSAGES/sphinx.po
sphinx_idf_theme/locale/tr/LC_MESSAGES/sphinx.mo
sphinx_idf_theme/locale/tr/LC_MESSAGES/sphinx.po
sphinx_idf_theme/locale/zh_CN/LC_MESSAGES/sphinx.mo
sphinx_idf_theme/locale/zh_CN/LC_MESSAGES/sphinx.po
sphinx_idf_theme/static/css/badge_only.css
sphinx_idf_theme/static/css/theme.css
sphinx_idf_theme/static/css/fonts/Roboto-Slab-Bold.woff
sphinx_idf_theme-2.0.1.dist-info/LICENSE
sphinx_idf_theme-2.0.1.dist-info/METADATA
sphinx_idf_theme-2.0.1.dist-info/WHEEL
sphinx_idf_theme-2.0.1.dist-info/entry_points.txt
sphinx_idf_theme-2.0.1.dist-info/top_level.txt
sphinx_idf_theme-2.0.1.dist-info/RECORD
