Metadata-Version: 2.1
Name: sphinx-idf-theme
Version: 2.0.1
Summary: IDF theme for Sphinx, based on Read The Docs theme
Home-page: https://github.com/espressif/sphinx_idf_theme
Author: Dave Snider, Read the Docs, Inc. & contributors, modified by Espressif Systems (Shanghai) Co Ltd
Author-email: 
License: MIT
Project-URL: Homepage, https://github.com/espressif/
Project-URL: Source Code, https://github.com/espressif/sphinx_idf_theme
Project-URL: Issue Tracker, https://github.com/espressif/sphinx_idf_theme/issues
Platform: UNKNOWN
Classifier: Framework :: Sphinx
Classifier: Framework :: Sphinx :: Theme
Classifier: Development Status :: 5 - Production/Stable
Classifier: License :: OSI Approved :: MIT License
Classifier: Environment :: Console
Classifier: Environment :: Web Environment
Classifier: Intended Audience :: Developers
Classifier: Programming Language :: Python :: 3
Classifier: Programming Language :: Python :: 3 :: Only
Classifier: Programming Language :: Python :: 3.6
Classifier: Programming Language :: Python :: 3.7
Classifier: Programming Language :: Python :: 3.8
Classifier: Programming Language :: Python :: 3.9
Classifier: Programming Language :: Python :: 3.10
Classifier: Programming Language :: Python :: 3.11
Classifier: Operating System :: OS Independent
Classifier: Topic :: Documentation
Classifier: Topic :: Software Development :: Documentation
Requires-Python: >=3.6
Requires-Dist: sphinx <8,>=5
Requires-Dist: docutils <0.21
Requires-Dist: sphinxcontrib-jquery <5,>=4
Provides-Extra: dev
Requires-Dist: transifex-client ; extra == 'dev'
Requires-Dist: sphinxcontrib-httpdomain ; extra == 'dev'
Requires-Dist: bump2version ; extra == 'dev'
Requires-Dist: wheel ; extra == 'dev'
